hetio/__init__.py
hetio/abbreviation.py
hetio/hetnet.py
hetio/matrix.py
hetio/neo4j.py
hetio/pathtools.py
hetio/permute.py
hetio/readwrite.py
hetio/stats.py
hetnetpy/__init__.py
hetnetpy/abbreviation.py
hetnetpy/hetnet.py
hetnetpy/matrix.py
hetnetpy/neo4j.py
hetnetpy/pathtools.py
hetnetpy/permute.py
hetnetpy/readwrite.py
hetnetpy/stats.py
hetnetpy-0.3.1.dist-info/LICENSE-CC0.md
hetnetpy-0.3.1.dist-info/METADATA
hetnetpy-0.3.1.dist-info/WHEEL
hetnetpy-0.3.1.dist-info/top_level.txt
hetnetpy-0.3.1.dist-info/RECORD
