Metadata-Version: 2.1
Name: hetnetpy
Version: 0.3.1
Summary: Hetnets in Python
Home-page: https://github.com/hetio/hetnetpy
Maintainer: Daniel Himmelstein
Maintainer-email: daniel.himmelstein@gmail.com
License: CC0 1.0
Keywords: hetnet,graph,heterogeneous,network,neo4j,hetio,hetnetpy,dwpc,rephetio
Platform: UNKNOWN
Classifier: Intended Audience :: Science/Research
Classifier: Topic :: Scientific/Engineering :: Bio-Informatics
Classifier: Topic :: Scientific/Engineering :: Information Analysis
Classifier: License :: CC0 1.0 Universal (CC0 1.0) Public Domain Dedication
Classifier: Programming Language :: Python :: 3 :: Only
Requires-Python: >=3.6
License-File: LICENSE-CC0.md
Requires-Dist: regex
Provides-Extra: matrix
Requires-Dist: numpy ; extra == 'matrix'
Requires-Dist: scipy ; extra == 'matrix'
Provides-Extra: neo4j
Requires-Dist: pandas ; extra == 'neo4j'
Requires-Dist: py2neo ; extra == 'neo4j'
Requires-Dist: tqdm ; extra == 'neo4j'
Provides-Extra: stats
Requires-Dist: pandas ; extra == 'stats'
Requires-Dist: matplotlib ; extra == 'stats'
Requires-Dist: seaborn ; extra == 'stats'
Provides-Extra: test
Requires-Dist: neo4j ; extra == 'test'
Requires-Dist: numpy ; extra == 'test'
Requires-Dist: pandas ; extra == 'test'
Requires-Dist: py2neo ; extra == 'test'
Requires-Dist: pytest ; extra == 'test'
Requires-Dist: scipy ; extra == 'test'
Requires-Dist: tqdm ; extra == 'test'
